metapensiero/tool/tinject/__init__.py
metapensiero/tool/tinject/__main__.py
metapensiero/tool/tinject/action.py
metapensiero/tool/tinject/config.py
metapensiero/tool/tinject/state.py
metapensiero/tool/tinject/steps/__init__.py
metapensiero/tool/tinject/steps/changefile.py
metapensiero/tool/tinject/steps/createdir.py
metapensiero/tool/tinject/steps/createfile.py
metapensiero/tool/tinject/steps/prompt.py
metapensiero/tool/tinject/steps/pythonscript.py
metapensiero/tool/tinject/steps/repeat.py
metapensiero_tool_tinject-2.0.dist-info/METADATA
metapensiero_tool_tinject-2.0.dist-info/WHEEL
metapensiero_tool_tinject-2.0.dist-info/entry_points.txt
metapensiero_tool_tinject-2.0.dist-info/RECORD
