Metadata-Version: 2.1
Name: metapensiero.tool.tinject
Version: 2.0
Summary: Automate creation of sources
Keywords: YAML,Jinja2,scaffolding,skeleton
Author-Email: Lele Gaifax <lele@metapensiero.it>
License: GPL-3.0-or-later
Classifier: Environment :: Console
Classifier: Programming Language :: Python
Classifier: Programming Language :: Python :: 3
Classifier: Programming Language :: Python :: 3 :: Only
Classifier: Development Status :: 5 - Production/Stable
Classifier: Intended Audience :: Developers
Classifier: License :: OSI Approved :: GNU General Public License v3 or later (GPLv3+)
Classifier: Topic :: Software Development
Classifier: Topic :: Utilities
Project-URL: Changelog, https://gitlab.com/metapensiero/metapensiero.tool.tinject/-/blob/master/CHANGES.rst
Project-URL: Source, https://gitlab.com/metapensiero/metapensiero.tool.tinject
Requires-Python: >=3.9
Requires-Dist: jinja2
Requires-Dist: jinja2-time
Requires-Dist: questionary
Requires-Dist: ruamel.yaml
Provides-Extra: dev
Requires-Dist: build; extra == "dev"
Requires-Dist: bump-my-version; extra == "dev"
Requires-Dist: tomli; extra == "dev"
Requires-Dist: twine; extra == "dev"
